LICENSE.md
plex_watched_sync/__init__.py
plex_watched_sync/cli.py
plex_watched_sync/log.py
plex_watched_sync/sync.py
plex_watched_sync-0.1.1.dist-info/entry_points.txt
plex_watched_sync-0.1.1.dist-info/LICENSE.md
plex_watched_sync-0.1.1.dist-info/WHEEL
plex_watched_sync-0.1.1.dist-info/METADATA
plex_watched_sync-0.1.1.dist-info/RECORD
